.appveyor.yml
.checkignore
.coveragerc
.environment.yml
.gitignore
.pre-commit-config.yaml
.readthedocs.yml
.travis.yml
AUTHORS.rst
CHANGELOG.rst
CITATION.cff
CODE_OF_CONDUCT.md
CONTRIBUTING.rst
LICENSE.txt
MANIFEST.in
README.rst
mypy.ini
requirements-docs.txt
requirements.txt
setup.cfg
setup.py
.github/ISSUE_TEMPLATE/bug_report.md
.github/ISSUE_TEMPLATE/feature_request.md
.github/ISSUE_TEMPLATE/release-smif.md
ci/coverage.sh
ci/install.sh
docs/Makefile
docs/authors.rst
docs/changelog.rst
docs/concepts.rst
docs/conf.py
docs/contributing.rst
docs/decisions.rst
docs/developers.rst
docs/getting_started.rst
docs/index.rst
docs/installation.rst
docs/license.rst
docs/project_configuration.rst
docs/simulation_models.rst
docs/_static/theme_tweaks.css
docs/_templates/README.txt
docs/_templates/module.rst
docs/_templates/package.rst
docs/gui/configure-narrative-set.png
docs/gui/configure-narratives.png
docs/gui/configure-scenario-set.png
docs/gui/configure-sector-models.png
docs/gui/configure-sos-model-run.png
docs/gui/configure-sos-models.png
docs/gui/configure.png
docs/gui/jobs-runner.png
docs/gui/jobs.png
docs/gui/screenshot.sh
docs/gui/welcome.png
docs/uml/classes_smif.png
docs/uml/config_flow.uml
docs/uml/convert_uml.sh
docs/uml/data_flow.png
docs/uml/data_flow.uml
docs/uml/data_handle.png
docs/uml/data_handle.uml
docs/uml/decision-simulation.png
docs/uml/decision-simulation.uml
docs/uml/decisions_flow.uml
docs/uml/error_boundaries.png
docs/uml/error_boundaries.uml
docs/uml/intervention.png
docs/uml/intervention.uml
docs/uml/packages_smif.png
docs/uml/resolution_sequence.uml
docs/uml/run_decisions.uml
docs/uml/run_model.uml
docs/uml/run_model_alternative.uml
docs/uml/run_pyreverse.sh
docs/uml/run_sos_model.uml
docs/uml/sequence.uml
docs/uml/smif.uml
docs/uml/smif_composite.png
docs/uml/smif_composite.uml
docs/uml/smif_composite_001.png
docs/uml/smif_composite_002.png
docs/uml/smif_composite_003.png
src/smif/__init__.py
src/smif/exception.py
src/smif.egg-info/PKG-INFO
src/smif.egg-info/SOURCES.txt
src/smif.egg-info/dependency_links.txt
src/smif.egg-info/entry_points.txt
src/smif.egg-info/requires.txt
src/smif.egg-info/top_level.txt
src/smif.egg-info/zip-safe
src/smif/app/.babelrc
