Metadata-Version: 2.1
Name: smif
Version: 1.3.1
Summary: Simulation Modelling Integration Framework
Home-page: http://www.itrc.org.uk
Author: Will Usher, Tom Russell, Roald Schoenmakers, Craig Robson, Fergus Cooper, Thibault Lestang, Rose Dickinson
Author-email: william.usher@ouce.ox.ac.uk
License: mit
Platform: any
Classifier: Development Status :: 4 - Beta
Classifier: Programming Language :: Python :: 3
Classifier: Programming Language :: JavaScript
Classifier: Intended Audience :: Science/Research
Classifier: License :: OSI Approved :: MIT License
Classifier: Natural Language :: English
Classifier: Topic :: Scientific/Engineering
Provides-Extra: win32
Provides-Extra: spatial
Provides-Extra: data
Provides-Extra: database
